azure/mgmt/dnsresolver/__init__.py
azure/mgmt/dnsresolver/_configuration.py
azure/mgmt/dnsresolver/_dns_resolver_management_client.py
azure/mgmt/dnsresolver/_patch.py
azure/mgmt/dnsresolver/_version.py
azure/mgmt/dnsresolver/py.typed
azure/mgmt/dnsresolver/_utils/__init__.py
azure/mgmt/dnsresolver/_utils/serialization.py
azure/mgmt/dnsresolver/aio/__init__.py
azure/mgmt/dnsresolver/aio/_configuration.py
azure/mgmt/dnsresolver/aio/_dns_resolver_management_client.py
azure/mgmt/dnsresolver/aio/_patch.py
azure/mgmt/dnsresolver/aio/operations/__init__.py
azure/mgmt/dnsresolver/aio/operations/_dns_forwarding_rulesets_operations.py
azure/mgmt/dnsresolver/aio/operations/_dns_resolver_domain_lists_operations.py
azure/mgmt/dnsresolver/aio/operations/_dns_resolver_policies_operations.py
azure/mgmt/dnsresolver/aio/operations/_dns_resolver_policy_virtual_network_links_operations.py
azure/mgmt/dnsresolver/aio/operations/_dns_resolvers_operations.py
azure/mgmt/dnsresolver/aio/operations/_dns_security_rules_operations.py
azure/mgmt/dnsresolver/aio/operations/_forwarding_rules_operations.py
azure/mgmt/dnsresolver/aio/operations/_inbound_endpoints_operations.py
azure/mgmt/dnsresolver/aio/operations/_outbound_endpoints_operations.py
azure/mgmt/dnsresolver/aio/operations/_patch.py
azure/mgmt/dnsresolver/aio/operations/_virtual_network_links_operations.py
azure/mgmt/dnsresolver/models/__init__.py
azure/mgmt/dnsresolver/models/_dns_resolver_management_client_enums.py
azure/mgmt/dnsresolver/models/_models_py3.py
azure/mgmt/dnsresolver/models/_patch.py
azure/mgmt/dnsresolver/operations/__init__.py
azure/mgmt/dnsresolver/operations/_dns_forwarding_rulesets_operations.py
azure/mgmt/dnsresolver/operations/_dns_resolver_domain_lists_operations.py
azure/mgmt/dnsresolver/operations/_dns_resolver_policies_operations.py
azure/mgmt/dnsresolver/operations/_dns_resolver_policy_virtual_network_links_operations.py
azure/mgmt/dnsresolver/operations/_dns_resolvers_operations.py
azure_mgmt_dnsresolver-1.1.0.dist-info/LICENSE
azure_mgmt_dnsresolver-1.1.0.dist-info/METADATA
azure_mgmt_dnsresolver-1.1.0.dist-info/WHEEL
azure_mgmt_dnsresolver-1.1.0.dist-info/top_level.txt
azure_mgmt_dnsresolver-1.1.0.dist-info/RECORD
